arsls/__init__.py
arsls-1.0.dist-info/LICENSE
arsls-1.0.dist-info/METADATA
arsls-1.0.dist-info/WHEEL
arsls-1.0.dist-info/entry_points.txt
arsls-1.0.dist-info/top_level.txt
arsls-1.0.dist-info/RECORD
