Metadata-Version: 2.1
Name: arsls
Version: 1.0
Summary: A simple URL Shortener with GUI made using CustomTkinter.
Home-page: https://github.com/e500ky/arsls
Author: ArsTech
Author-email: arstechai@gmail.com
Classifier: Programming Language :: Python :: 3
Classifier: License :: OSI Approved :: MIT License
Classifier: Operating System :: OS Independent
Requires-Python: >=3.8
License-File: LICENSE
Requires-Dist: customtkinter
Requires-Dist: pyshorteners
Requires-Dist: pyperclip
